invenio_subjects_fast/__init__.py
invenio_subjects_fast/cli.py
invenio_subjects_fast/converter.py
invenio_subjects_fast/downloader.py
invenio_subjects_fast/downloads/.gitkeep
invenio_subjects_fast/vocabularies/__init__.py
invenio_subjects_fast/vocabularies/subjects_fast_chronological.jsonl
invenio_subjects_fast/vocabularies/subjects_fast_corporate.jsonl
invenio_subjects_fast/vocabularies/subjects_fast_event.jsonl
invenio_subjects_fast/vocabularies/subjects_fast_formgenre.jsonl
invenio_subjects_fast/vocabularies/subjects_fast_geographic.jsonl
invenio_subjects_fast/vocabularies/subjects_fast_meeting.jsonl
invenio_subjects_fast/vocabularies/subjects_fast_personal.jsonl
invenio_subjects_fast/vocabularies/subjects_fast_title.jsonl
invenio_subjects_fast/vocabularies/subjects_fast_topical.jsonl
invenio_subjects_fast/vocabularies/vocabularies.yaml
invenio_subjects_fast-2023.7.5.dist-info/LICENSE
invenio_subjects_fast-2023.7.5.dist-info/METADATA
invenio_subjects_fast-2023.7.5.dist-info/WHEEL
invenio_subjects_fast-2023.7.5.dist-info/entry_points.txt
invenio_subjects_fast-2023.7.5.dist-info/top_level.txt
invenio_subjects_fast-2023.7.5.dist-info/RECORD
