Metadata-Version: 2.1
Name: invenio-subjects-fast
Version: 2023.7.5
Summary: Provides the FAST faceted subject vocabulary for InvenioRDM
Home-page: https://github.com/MESH-Research/invenio-subjects-fast
Author: MESH Research
Author-email: MESH Research <scottia4@msu.edu>
License: MIT License
Project-URL: Homepage, https://github.com/MESH-Research/invenio-subjects-fast
Keywords: invenio,inveniordm,subjects,FAST
Platform: any
Classifier: License :: OSI Approved :: MIT License
Classifier: Programming Language :: Python
Classifier: Programming Language :: Python :: 3
Classifier: Programming Language :: Python :: 3.9
Classifier: Environment :: Web Environment
Classifier: Intended Audience :: Developers
Classifier: Operating System :: OS Independent
Classifier: Topic :: Internet :: WWW/HTTP :: Dynamic Content
Classifier: Topic :: Software Development :: Libraries :: Python Modules
Requires-Python: >=3.9
License-File: LICENSE
Requires-Dist: click (>=7.0)
Provides-Extra: all
Requires-Dist: pytest (>=7.3.2) ; extra == 'all'
Requires-Dist: responses (>=0.23.1) ; extra == 'all'
Requires-Dist: pyyaml (>=5.4.1) ; extra == 'all'
Requires-Dist: pytest-runner ; extra == 'all'
Requires-Dist: halo (~=0.0.31) ; extra == 'all'
Requires-Dist: requests (>=2.25.1) ; extra == 'all'
Requires-Dist: tqdm (~=4.65.0) ; extra == 'all'
Provides-Extra: dev
Requires-Dist: halo (~=0.0.31) ; extra == 'dev'
Requires-Dist: requests (>=2.25.1) ; extra == 'dev'
Requires-Dist: tqdm (~=4.65.0) ; extra == 'dev'
Requires-Dist: check-manifest ; extra == 'dev'
Requires-Dist: pip-tools ; extra == 'dev'
Requires-Dist: pytest (>=7.3.2) ; extra == 'dev'
Requires-Dist: pytest-runner ; extra == 'dev'
Requires-Dist: pyyaml (>=5.4.1) ; extra == 'dev'
Requires-Dist: responses (>=0.23.1) ; extra == 'dev'
Requires-Dist: tqdm (>=4.65.0) ; extra == 'dev'
Provides-Extra: tests
Requires-Dist: pytest (>=7.3.2) ; extra == 'tests'
Requires-Dist: responses (>=0.23.1) ; extra == 'tests'
Requires-Dist: pyyaml (>=5.4.1) ; extra == 'tests'
Requires-Dist: pytest-runner ; extra == 'tests'
